include/ceres/autodiff_cost_function.h
include/ceres/autodiff_first_order_function.h
include/ceres/autodiff_manifold.h
include/ceres/c_api.h
include/ceres/ceres.h
include/ceres/conditioned_cost_function.h
include/ceres/constants.h
include/ceres/context.h
include/ceres/cost_function.h
include/ceres/cost_function_to_functor.h
include/ceres/covariance.h
include/ceres/crs_matrix.h
include/ceres/cubic_interpolation.h
include/ceres/dynamic_autodiff_cost_function.h
include/ceres/dynamic_cost_function.h
include/ceres/dynamic_cost_function_to_functor.h
include/ceres/dynamic_numeric_diff_cost_function.h
include/ceres/evaluation_callback.h
include/ceres/first_order_function.h
include/ceres/gradient_checker.h
include/ceres/gradient_problem.h
include/ceres/gradient_problem_solver.h
include/ceres/internal/array_selector.h
include/ceres/internal/autodiff.h
include/ceres/internal/config.h
include/ceres/internal/disable_warnings.h
include/ceres/internal/eigen.h
include/ceres/internal/euler_angles.h
include/ceres/internal/export.h
include/ceres/internal/fixed_array.h
include/ceres/internal/householder_vector.h
include/ceres/internal/integer_sequence_algorithm.h
include/ceres/internal/jet_traits.h
include/ceres/internal/line_parameterization.h
include/ceres/internal/memory.h
include/ceres/internal/miniglog/glog/logging.h
include/ceres/internal/numeric_diff.h
include/ceres/internal/parameter_dims.h
include/ceres/internal/port.h
include/ceres/internal/reenable_warnings.h
include/ceres/internal/sphere_manifold_functions.h
include/ceres/internal/variadic_evaluate.h
include/ceres/iteration_callback.h
include/ceres/jet.h
include/ceres/jet_fwd.h
include/ceres/line_manifold.h
include/ceres/loss_function.h
include/ceres/manifold.h
include/ceres/manifold_test_utils.h
include/ceres/normal_prior.h
include/ceres/numeric_diff_cost_function.h
include/ceres/numeric_diff_first_order_function.h
include/ceres/numeric_diff_options.h
include/ceres/ordered_groups.h
include/ceres/problem.h
resfo_utilities-0.5.4.dist-info/METADATA
resfo_utilities-0.5.4.dist-info/WHEEL
resfo_utilities-0.5.4.dist-info/licenses/LICENSE.md
resfo_utilities-0.5.4.dist-info/RECORD
