Metadata-Version: 2.4
Name: resfo-utilities
Version: 0.5.4
Summary: A utility library for working with the output of reservoir simulators.
Author-Email: Equinor <fg_sib-scout@equinor.com>
Maintainer-Email: Eivind Jahren <ejah@equinor.com>, =?utf-8?q?H=C3=A5kon_Steinkopf_S=C3=B8hoel?= <hsoho@equinor.com>
License-Expression: LGPL-3.0-or-later
Classifier: Development Status :: 1 - Planning
Classifier: Programming Language :: Python
Classifier: Programming Language :: Python :: 3.11
Classifier: Programming Language :: Python :: 3.12
Classifier: Programming Language :: Python :: 3.13
Classifier: Programming Language :: Python :: 3.14
Project-URL: Homepage, https://github.com/equinor/resfo-utilities
Project-URL: Repository, https://github.com/equinor/resfo-utilities
Project-URL: Documentation, https://resfo-utilities.readthedocs.io/en/stable/
Project-URL: Bug Tracker, https://github.com/equinor/resfo-utilities/issues
Requires-Python: <=3.15,>=3.11
Requires-Dist: numpy
Requires-Dist: resfo>=5
Requires-Dist: scipy
Requires-Dist: natsort
Provides-Extra: testing
Requires-Dist: hypothesis; extra == "testing"
Requires-Dist: pydantic; extra == "testing"
Provides-Extra: doc
Requires-Dist: sphinx; extra == "doc"
Requires-Dist: sphinx-rtd-theme; extra == "doc"
Provides-Extra: dev
Requires-Dist: pytest; extra == "dev"
Requires-Dist: pre-commit; extra == "dev"
Requires-Dist: mypy; extra == "dev"
Requires-Dist: pytest-benchmark; extra == "dev"
Requires-Dist: scipy-stubs; extra == "dev"
